README.txt
setup.py
src/django_processedfilefield.egg-info/PKG-INFO
src/django_processedfilefield.egg-info/SOURCES.txt
src/django_processedfilefield.egg-info/dependency_links.txt
src/django_processedfilefield.egg-info/top_level.txt
src/processedfilefield/__init__.py
src/processedfilefield/fields.py
src/processedfilefield/mixins.py