Metadata-Version: 1.0
Name: django-processedfilefield
Version: 0.2
Summary: Post-processing for Django FileFields.
Home-page: https://github.com/nathforge/django-processedfilefield
Author: Nathan Reynolds
Author-email: email@nreynolds.co.uk
License: UNKNOWN
Platform: UNKNOWN
